<?xml version="1.0" encoding="UTF-8"?>
<mappings xmlns="http://dozer.sourceforge.net" xmlns:xsi="http://www.w3.org/2001/XMLSchema-instance"
	xsi:schemaLocation="http://dozer.sourceforge.net http://dozer.sourceforge.net/schema/beanmapping.xsd">

	<!-- NOTE: the client depends on lexicographical ordering to sort dates -->
	<mapping date-format="yyyy-MM-dd">
		<class-a>com.prealpha.extempdb.domain.Article</class-a>
		<class-b>com.prealpha.extempdb.instance.shared.dto.ArticleDto</class-b>
	</mapping>
	
	<mapping date-format="yyyy-MM-dd">
		<class-a>com.prealpha.extempdb.domain.ArticleUrl</class-a>
		<class-b>com.prealpha.extempdb.instance.shared.dto.ArticleUrlDto</class-b>
	</mapping>

</mappings>